{
  "lastUpdated": "May 5, 2026",

  "kpiMeta": {
    "promoConfigs":     { "label": "Promo Configs Built",        "sub": "offers & generosity setups", "unit": "",  "lowerBetter": false, "target": null },
    "cycleTime":        { "label": "Cycle Time",                  "sub": "avg. brief to live config",  "unit": "d", "lowerBetter": true,  "target": 3    },
    "configAccuracy":   { "label": "Config Accuracy",             "sub": "first-time-right rate",      "unit": "%", "lowerBetter": false, "target": 99   },
    "slaAdherence":     { "label": "SLA Adherence",               "sub": "on-time config delivery",    "unit": "%", "lowerBetter": false, "target": 90   },
    "requestsTracked":  { "label": "Requests Tracked in Asana",   "sub": "of all intake requests",     "unit": "%", "lowerBetter": false, "target": 100  },
    "generosityErrors": { "label": "Generosity Errors",           "sub": "post-deployment",            "unit": "",  "lowerBetter": true,  "target": 0    }
  },

  "months": [
    {
      "id": "march-2026",
      "label": "March 2026",
      "kpi": {
        "promoConfigs":     { "value": 1629,  "detail": null },
        "cycleTime":        { "value": 2.25,  "detail": null },
        "configAccuracy":   { "value": 98.3,  "detail": "1,602 / 1,629 first-time-right" },
        "slaAdherence":     { "value": 92.45, "detail": "4 misses / 53 tasks" },
        "requestsTracked":  { "value": 100,   "detail": null },
        "generosityErrors": { "value": 6,     "detail": null }
      },
      "operators": [
        { "name": "Don",     "value": 2   },
        { "name": "Aunye",   "value": 235 },
        { "name": "Billy",   "value": 2   },
        { "name": "Michael", "value": 76  },
        { "name": "Spencer", "value": 0   },
        { "name": "Jordan",  "value": 390 },
        { "name": "Jenna",   "value": 63  },
        { "name": "Eddie",   "value": 12  },
        { "name": "Jonah",   "value": 201 },
        { "name": "Stephen", "value": 482 },
        { "name": "Elena",   "value": 0   },
        { "name": "Camille", "value": 0   },
        { "name": "Nikki",   "value": 166 }
      ]
    },
    {
      "id": "april-2026",
      "label": "April 2026",
      "kpi": {
        "promoConfigs":     { "value": 1523,  "detail": null },
        "cycleTime":        { "value": 2.63,  "detail": null },
        "configAccuracy":   { "value": 98.1,  "detail": "1,494 / 1,523 first-time-right" },
        "slaAdherence":     { "value": 91.78, "detail": "6 misses / 73 tasks" },
        "requestsTracked":  { "value": 100,   "detail": null },
        "generosityErrors": { "value": 7,     "detail": null }
      },
      "operators": [
        { "name": "Don",     "value": 1   },
        { "name": "Aunye",   "value": 340 },
        { "name": "Billy",   "value": 1   },
        { "name": "Michael", "value": 50  },
        { "name": "Spencer", "value": 8   },
        { "name": "Jordan",  "value": 477 },
        { "name": "Jenna",   "value": 75  },
        { "name": "Eddie",   "value": 10  },
        { "name": "Jonah",   "value": 130 },
        { "name": "Stephen", "value": 306 },
        { "name": "Elena",   "value": 48  },
        { "name": "Camille", "value": 34  },
        { "name": "Nikki",   "value": 43  }
      ]
    },
    {
      "id": "may-2026",
      "label": "May 2026",
      "kpi": {
        "promoConfigs":     { "value": null, "detail": null },
        "cycleTime":        { "value": null, "detail": null },
        "configAccuracy":   { "value": null, "detail": null },
        "slaAdherence":     { "value": null, "detail": null },
        "requestsTracked":  { "value": null, "detail": null },
        "generosityErrors": { "value": null, "detail": null }
      },
      "operators": [
        { "name": "Don",     "value": null },
        { "name": "Aunye",   "value": null },
        { "name": "Billy",   "value": null },
        { "name": "Michael", "value": null },
        { "name": "Spencer", "value": null },
        { "name": "Jordan",  "value": null },
        { "name": "Jenna",   "value": null },
        { "name": "Eddie",   "value": null },
        { "name": "Jonah",   "value": null },
        { "name": "Stephen", "value": null },
        { "name": "Elena",   "value": null },
        { "name": "Camille", "value": null },
        { "name": "Nikki",   "value": null }
      ]
    }
  ],

  "projects": [
    {
      "name": "AI Contextual QA Tool",
      "status": "planning",
      "phase": "Discovery",
      "pct": 5,
      "startDate": null,
      "targetDate": null,
      "owner": null,
      "desc": "Ingests original request information from Asana alongside the configurations of built promotions, compares the two for accuracy, and outputs a report summarising correct elements while alerting on those that are incorrect or require human review."
    },
    {
      "name": "AI Seeded Promo Creation Tool",
      "status": "planning",
      "phase": "Discovery",
      "pct": 5,
      "startDate": null,
      "targetDate": null,
      "owner": null,
      "desc": "Ingests a \"seed version\" of a promotion and generates an output CSV containing all other required versions, enabling bulk creation of promotion variants from a single source record."
    },
    {
      "name": "AI Workload Tool",
      "status": "planning",
      "phase": "Discovery",
      "pct": 5,
      "startDate": null,
      "targetDate": null,
      "owner": null,
      "desc": "Identifies request volume in the backlog alongside team member availability, producing forecasts and task assignments that ensure all required work is completed within SLA."
    },
    {
      "name": "AI Daily Standup Tool",
      "status": "planning",
      "phase": "Discovery",
      "pct": 5,
      "startDate": null,
      "targetDate": null,
      "owner": null,
      "desc": "An agent that reviews incomplete Asana requests and outputs a daily summary of open items and required follow-ups, surfacing blockers so tasks are ready to build."
    }
  ]
}
